{"last_cached": "2025-01-29 08:58:22.479781", "dateMostRecent": "Wednesday, January 8th, 2025", "dateWeekStart": "Thursday, January 2nd, 2025", "dateYearStart": "Wednesday, January 10th, 2024", "subwayWeeklyRidership": 21945101, "subwayYearlyRidership": 1192536128, "subwayMaxAnnualDateRidership": 4527892, "subwayMaxAnnualDate": "Thursday, December 12th, 2024", "subwayMinAnnualDateRidership": 1378374, "subwayMinAnnualDate": "Wednesday, December 25th, 2024", "subwayMaxDailyRidershipWeekly": 3830616, "subwayMaxDailyDateWeekly": "Wednesday, January 8th, 2025", "subwayMaxAnnualDay": "Wednesday", "subwayMaxMeanDayRidership": 3826836.433962264, "subwayMinAnnualDay": "Sunday", "subwayMinMeanDayRidership": 1969549.6923076923, "subwayStationMaxRidershipWeeklyStation": ["Times Sq-42 St (N,Q,R,W,S,1,2,3,7)/42 St (A,C,E)", "Grand Central-42 St (S,4,5,6,7)", "34 St-Herald Sq (B,D,F,M,N,Q,R,W)", "14 St-Union Sq (L,N,Q,R,W,4,5,6)", "Fulton St (A,C,J,Z,2,3,4,5)", "34 St-Penn Station (1,2,3)", "34 St-Penn Station (A,C,E)", "Flushing-Main St (7)", "74-Broadway (7)/Jackson Hts-Roosevelt Av (E,F,M,R)", "59 St-Columbus Circle (A,B,C,D,1)", "47-50 Sts-Rockefeller Ctr (B,D,F,M)", "Chambers St (A,C)/WTC (E)/Park Pl (2,3)/Cortlandt (R,W)", "Lexington Av-53 St (E,M)/51 St (6)", "Bryant Pk (B,D,F,M)/5 Av (7)", "Lexington Av (N,R,W)/59 St (4,5,6)", "Canal St (J,N,Q,R,W,Z,6)", "Atlantic Av-Barclays Ctr (B,D,N,Q,R,2,3,4,5)", "86 St (4,5,6)", "14 St (A,C,E)/8 Av (L)", "14 St (F,M,1,2,3)/6 Av (L)", "72 St (1,2,3)", "Broadway-Lafayette St (B,D,F,M)/Bleecker St (6)", "W 4 St-Wash Sq (A,C,E,B,D,F,M)", "96 St (1,2,3)", "57 St-7 Av (N,Q,R,W)", "Bedford Av (L)", "72 St (Q)", "Delancey St (F)/Essex St (J,M,Z)", "49 St (N,R,W)", "Jay St-MetroTech (A,C,F,R)", "Jamaica Center-Parsons/Archer (E,J,Z)", "50 St (1)", "34 St-Hudson Yards (7)", "1 Av (L)", "South Ferry (1)/Whitehall St (R,W)", "Sutphin Blvd-Archer Av-JFK Airport (E,J,Z)", "77 St (6)", "Junction Blvd (7)", "103 St-Corona Plaza (7)", "23 St (F,M)", "33 St (6)", "86 St (Q)", "Court St (R)/Borough Hall (2,3,4,5)", "Forest Hills-71 Av (E,F,M,R)", "Court Sq (E,G,M,7)", "Brooklyn Bridge-City Hall (4,5,6)/Chambers St (J,Z)", "161 St-Yankee Stadium (B,D,4)", "125 St (4,5,6)", "Crown Hts-Utica Av (3,4)", "Myrtle-Wyckoff Avs (L,M)", "168 St (A,C,1)", "66 St-Lincoln Center (1)", "Grand St (B,D)", "50 St (C,E)", "90 St-Elmhurst Av (7)", "23 St (6)", "Kew Gardens-Union Tpke (E,F)", "DeKalb Av (B,Q,R)", "Bowling Green (4,5)", "125 St (A,C,B,D)", "23 St (C,E)", "5 Av/53 St (E,M)", "28 St (6)", "Grand Av-Newtown (M,R)", "86 St (1)", "Woodhaven Blvd (M,R)", "23 St (R,W)", "96 St (Q)", "36 St (D,N,R)", "Kings Hwy (B,Q)", "3 Av-149 St (2,5)", "Wall St (2,3)", "145 St (A,C,B,D)", "79 St (1)", "Jamaica-179 St (F)", "2 Av (F)", "7 Av (E,B,D)", "68 St-Hunter College (6)", "Lexington Av/63 St (F,Q)", "Lorimer St (L)/Metropolitan Av (G)", "96 St (6)", "Chambers St (1,2,3)", "61 St-Woodside (7)", "WTC Cortlandt (1)", "Flatbush Av-Brooklyn College (2,5)", "Vernon Blvd-Jackson Av (7)", "Nostrand Av (A,C)", "Canal St (A,C,E)", "5 Av/59 St (N,R,W)", "Queens Plaza (E,M,R)", "East Broadway (F)", "57 St (F)", "Spring St (C,E)", "Astor Pl (6)", "59 St (N,R)", "8 St-NYU (R,W)", "Wall St (4,5)", "York St (F)", "Astoria-Ditmars Blvd (N,W)", "Prince St (R,W)", "Franklin Av (2,3,4,5)/Botanic Garden (S)", "125 St (2,3)", "23 St (1)", "Houston St (1)", "30 Av (N,W)", "Elmhurst Av (M,R)", "63 Dr-Rego Park (M,R)", "Spring St (6)", "Utica Av (A,C)", "4 Av (F,G)/9 St (R)", "DeKalb Av (L)", "46 St-Bliss St (7)", "7 Av (F,G)", "Christopher St-Sheridan Sq (1)", "Queensboro Plaza (7,N,W)", "103 St (1)", "28 St (1)", "28 St (R,W)", "Coney Island-Stillwell Av (D,F,N,Q)", "8 Av (N)", "Broadway (N,W)", "Bergen St (F,G)", "Carroll St (F,G)", "Marcy Av (M,J,Z)", "103 St (6)", "Steinway St (M,R)", "Hoyt-Schermerhorn Sts (A,C,G)", "Cathedral Pkwy (110 St) (1)", "Sheepshead Bay (B,Q)", "82 St-Jackson Hts (7)", "116 St (6)", "135 St (2,3)", "Greenpoint Av (G)", "81 St-Museum of Natural History (C,B)", "Parkside Av (Q)", "111 St (7)", "Parkchester (6)", "181 St (1)", "Myrtle Av (M,J,Z)", "Nassau Av (G)", "157 St (1)", "149 St-Grand Concourse (2,4,5)", "137 St-City College (1)", "Astoria Blvd (N,W)", "145 St (1)", "21 St-Queensbridge (F)", "110 St (6)", "40 St-Lowery St (7)", "Jefferson St (L)", "Brighton Beach (B,Q)", "116 St (2,3)", "86 St (R)", "7 Av (B,Q)", "Graham Av (L)", "Prospect Park (B,Q,S)", "86 St (C,B)", "Church Av (F,G)", "Euclid Av (A,C)", "Church Av (2,5)", "Bedford-Nostrand Avs (G)", "Newkirk Plaza (B,Q)", "St George (SIR)", "Burnside Av (4)", "Nevins St (2,3,4,5)", "Roosevelt Island (F)", "175 St (A)", "High St (A,C)", "Hunts Point Av (6)", "Hoyt St (2,3)", "116 St-Columbia University (1)", "Fordham Rd (4)", "Halsey St (L)", "53 St (R)", "67 Av (M,R)", "Union St (R)", "181 St (A)", "Flushing Av (M,J)", "167 St (4)", "33 St-Rawson St (7)", "231 St (1)", "191 St (1)", "125 St (1)", "Morgan Av (L)", "E 180 St (2,5)", "Fulton St (G)", "72 St (C,B)", "169 St (F)", "Broadway Junction (A,C,J,L,Z)", "Bay Pkwy (D)", "18 St (1)", "Kingsbridge Rd (4)", "46 St (M,R)", "Rector St (1)", "Central Park North (110 St) (2,3)", "Inwood-207 St (A)", "Winthrop St (2,5)", "3 Av (L)", "Grand Army Plaza (2,3)", "Dyckman St (1)", "Grand St (L)", "Montrose Av (L)", "Parsons Blvd (F)", "Tremont Av (B,D)", "Fort Hamilton Pkwy (N)", "52 St (7)", "45 St (R)", "Fordham Rd (B,D)", "Avenue U (Q)", "Clark St (2,3)", "3 Av-138 St (6)", "Clinton-Washington Avs (C)", "36 Av (N,W)", "Northern Blvd (M,R)", "Simpson St (2,5)", "170 St (4)", "Bay Pkwy (N)", "Newkirk Av-Little Haiti (2,5)", "Gates Av (J,Z)", "79 St (D)", "Mosholu Pkwy (4)", "Pelham Pkwy (2,5)", "18 Av (D)", "Bay Ridge Av (R)", "69 St (7)", "Kingston-Throop Avs (C)", "Rockaway Blvd (A)", "Cortelyou Rd (Q)", "15 St-Prospect Park (F,G)", "167 St (B,D)", "Fort Hamilton Pkwy (F,G)", "Prospect Av (R)", "Broad St (J,Z)", "Beverley Rd (Q)", "Kosciuszko St (J)", "96 St (C,B)", "9 Av (D)", "Franklin St (1)", "Prospect Av (2,5)", "Sutter Av-Rutland Rd (3)", "207 St (1)", "Avenue M (Q)", "Clinton-Washington Avs (G)", "Ozone Park-Lefferts Blvd (A)", "Lafayette Av (C)", "Rockaway Av (C)", "Halsey St (J)", "Fresh Pond Rd (M)", "New Utrecht Av (N)/62 St (D)", "Sterling St (2,5)", "Kings Hwy (N)", "Gun Hill Rd (2,5)", "Woodlawn (4)", "Myrtle-Willoughby Avs (G)", "Classon Av (G)", "Franklin Av (C,S)", "Dyckman St (A)", "Van Cortlandt Park-242 St (1)", "Cathedral Pkwy (110 St) (C,B)", "Avenue J (Q)", "Norwood-205 St (D)", "Eastern Pkwy-Brooklyn Museum (2,3)", "Pelham Bay Park (6)", "20 Av (D)", "174 St (2,5)", "Rector St (R,W)", "Castle Hill Av (6)", "Elder Av (6)", "Broadway (G)", "71 St (D)", "Bedford Park Blvd (B,D)", "West Farms Sq-E Tremont Av (2,5)", "18 Av (N)", "Brook Av (6)", "116 St (C,B)", "Morrison Av-Soundview (6)", "Briarwood (E,F)", "Canal St (1)", "Kingsbridge Rd (B,D)", "Grant Av (A)", "176 St (4)", "Jackson Av (2,5)", "New Lots Av (3)", "Bergen St (2,3)", "Ralph Av (C)", "Bedford Park Blvd-Lehman College (4)", "Jamaica-Van Wyck (E)", "20 Av (N)", "Marble Hill-225 St (1)", "Kingston Av (3)", "Hunters Point Av (7)", "183 St (4)", "City Hall (R,W)", "Saratoga Av (3)", "Beverly Rd (2,5)", "Far Rockaway-Mott Av (A)", "Forest Av (M)", "Wilson Av (L)", "25 Av (D)", "Woodhaven Blvd (J,Z)", "Rockaway Av (3)", "77 St (R)", "Neck Rd (Q)", "Fort Hamilton Pkwy (D)", "170 St (B,D)", "Mt Eden Av (4)", "Sutphin Blvd (F)", "Knickerbocker Av (M)", "E 149 St (6)", "Lorimer St (M,J)", "Smith-9 Sts (F,G)", "238 St (1)", "Church Av (B,Q)", "Crescent St (J,Z)", "Bowery (J,Z)", "Freeman St (2,5)", "135 St (C,B)", "Howard Beach-JFK Airport (A)", "Bay Ridge-95 St (R)", "Middle Village-Metropolitan Av (M)", "Avenue U (N)", "80 St (A)", "Central Av (M)", "190 St (A)", "138 St-Grand Concourse (4,5)", "Ditmas Av (F)", "Westchester Sq-E Tremont Av (6)", "Wakefield-241 St (2)", "25 St (R)", "Allerton Av (2,5)", "182-183 Sts (B,D)", "39 Av-Dutch Kills (N,W)", "Kings Hwy (F)", "18 Av (F)", "Nostrand Av (3)", "Gun Hill Rd (5)", "36 St (M,R)", "Pennsylvania Av (3)", "75 St-Elderts Ln (J,Z)", "President St-Medgar Evers College (2,5)", "50 St (D)", "65 St (M,R)", "163 St-Amsterdam Av (C)", "Buhre Av (6)", "Harlem-148 St (3)", "103 St (C,B)", "Flushing Av (G)", "233 St (2,5)", "Eastchester-Dyre Av (5)", "174-175 Sts (B,D)", "Sutter Av (L)", "St Lawrence Av (6)", "75 Av (E,F)", "New Lots Av (L)", "Avenue H (Q)", "145 St (3)", "Ocean Pkwy (Q)", "Longwood Av (6)", "Bay 50 St (D)", "Seneca Av (M)", "Mets-Willets Point (7)", "104 St (J,Z)", "Livonia Av (L)", "Chauncey St (J,Z)", "Van Siclen Av (C)", "Intervale Av (2,5)", "Pelham Pkwy (5)", "Hewes St (M,J)", "225 St (2,5)", "Avenue N (F)", "Cypress Av (6)", "88 St (A)", "East 105 St (L)", "Atlantic Av (L)", "Bushwick Av-Aberdeen St (L)", "Junius St (3)", "Van Siclen Av (J,Z)", "155 St (B,D)", "Baychester Av (5)", "Shepherd Av (C)", "Avenue X (F)", "Morris Park (5)", "121 St (J,Z)", "111 St (J)", "Canarsie-Rockaway Pkwy (L)", "Avenue P (F)", "Nereid Av (2,5)", "86 St (N)", "Liberty Av (C)", "215 St (1)", "Zerega Av (6)", "155 St (C)", "219 St (2,5)", "Van Siclen Av (3)", "Burke Av (2,5)", "W 8 St-NY Aquarium (F,Q)", "Norwood Av (J,Z)", "55 St (D)", "Avenue U (F)", "Bronx Park East (2,5)", "111 St (A)", "21 St (G)", "Alabama Av (J)", "Cleveland St (J)", "Middletown Rd (6)", "Beach 67 St (A)", "85 St-Forest Pkwy (J)", "Park Pl (S)", "Whitlock Av (6)", "104 St (A)", "Avenue I (F)", "Neptune Av (F)", "E 143 St-St Mary's St (6)", "Beach 60 St (A)", "Beach 25 St (A)", "Bay Pkwy (F)", "Cypress Hills (J)", "Aqueduct-N Conduit Av (A)", "Tompkinsville (SIR)", "Beach 44 St (A)", "Rockaway Park-Beach 116 St (A,S)", "Aqueduct Racetrack (A)", "Beach 36 St (A)", "Beach 90 St (A,S)", "Beach 98 St (A,S)", "Broad Channel (A,S)", "Beach 105 St (A,S)"], "subwayStationMaxRidershipWeeklyBorough": ["Manhattan", "Manhattan", "Manhattan", "Manhattan", "Manhattan", "Manhattan", "Manhattan", "Queens", "Queens", "Manhattan", "Manhattan", "Manhattan", "Manhattan", "Manhattan", "Manhattan", "Manhattan", "Brooklyn", "Manhattan", "Manhattan", "Manhattan", "Manhattan", "Manhattan", "Manhattan", "Manhattan", "Manhattan", "Brooklyn", "Manhattan", "Manhattan", "Manhattan", "Brooklyn", "Queens", "Manhattan", "Manhattan", "Manhattan", "Manhattan", "Queens", "Manhattan", "Queens", "Queens", "Manhattan", "Manhattan", "Manhattan", "Brooklyn", "Queens", "Queens", "Manhattan", "Bronx", "Manhattan", "Brooklyn", "Brooklyn", "Manhattan", "Manhattan", "Manhattan", "Manhattan", "Queens", "Manhattan", "Queens", "Brooklyn", "Manhattan", "Manhattan", "Manhattan", "Manhattan", "Manhattan", "Queens", "Manhattan", "Queens", "Manhattan", "Manhattan", "Brooklyn", "Brooklyn", "Bronx", "Manhattan", "Manhattan", "Manhattan", "Queens", "Manhattan", "Manhattan", "Manhattan", "Manhattan", "Brooklyn", "Manhattan", "Manhattan", "Queens", "Manhattan", "Brooklyn", "Queens", "Brooklyn", "Manhattan", "Manhattan", "Queens", "Manhattan", "Manhattan", "Manhattan", "Manhattan", "Brooklyn", "Manhattan", "Manhattan", "Brooklyn", "Queens", "Manhattan", "Brooklyn", "Manhattan", "Manhattan", "Manhattan", "Queens", "Queens", "Queens", "Manhattan", "Brooklyn", "Brooklyn", "Brooklyn", "Queens", "Brooklyn", "Manhattan", "Queens", "Manhattan", "Manhattan", "Manhattan", "Brooklyn", "Brooklyn", "Queens", "Brooklyn", "Brooklyn", "Brooklyn", "Manhattan", "Queens", "Brooklyn", "Manhattan", "Brooklyn", "Queens", "Manhattan", "Manhattan", "Brooklyn", "Manhattan", "Brooklyn", "Queens", "Bronx", "Manhattan", "Brooklyn", "Brooklyn", "Manhattan", "Bronx", "Manhattan", "Queens", "Manhattan", "Queens", "Manhattan", "Queens", "Brooklyn", "Brooklyn", "Manhattan", "Brooklyn", "Brooklyn", "Brooklyn", "Brooklyn", "Manhattan", "Brooklyn", "Brooklyn", "Brooklyn", "Brooklyn", "Brooklyn", "Staten Island", "Bronx", "Brooklyn", "Manhattan", "Manhattan", "Brooklyn", "Bronx", "Brooklyn", "Manhattan", "Bronx", "Queens", "Brooklyn", "Queens", "Brooklyn", "Manhattan", "Brooklyn", "Bronx", "Queens", "Bronx", "Manhattan", "Manhattan", "Brooklyn", "Bronx", "Brooklyn", "Manhattan", "Queens", "Brooklyn", "Brooklyn", "Manhattan", "Bronx", "Queens", "Manhattan", "Manhattan", "Manhattan", "Brooklyn", "Manhattan", "Brooklyn", "Manhattan", "Brooklyn", "Brooklyn", "Queens", "Bronx", "Brooklyn", "Queens", "Brooklyn", "Bronx", "Brooklyn", "Brooklyn", "Bronx", "Brooklyn", "Queens", "Queens", "Bronx", "Bronx", "Brooklyn", "Brooklyn", "Brooklyn", "Brooklyn", "Bronx", "Bronx", "Brooklyn", "Brooklyn", "Queens", "Brooklyn", "Queens", "Brooklyn", "Brooklyn", "Bronx", "Brooklyn", "Brooklyn", "Manhattan", "Brooklyn", "Brooklyn", "Manhattan", "Brooklyn", "Manhattan", "Bronx", "Brooklyn", "Manhattan", "Brooklyn", "Brooklyn", "Queens", "Brooklyn", "Brooklyn", "Brooklyn", "Queens", "Brooklyn", "Brooklyn", "Brooklyn", "Bronx", "Bronx", "Brooklyn", "Brooklyn", "Brooklyn", "Manhattan", "Bronx", "Manhattan", "Brooklyn", "Bronx", "Brooklyn", "Bronx", "Brooklyn", "Bronx", "Manhattan", "Bronx", "Bronx", "Brooklyn", "Brooklyn", "Bronx", "Bronx", "Brooklyn", "Bronx", "Manhattan", "Bronx", "Queens", "Manhattan", "Bronx", "Brooklyn", "Bronx", "Bronx", "Brooklyn", "Brooklyn", "Brooklyn", "Bronx", "Queens", "Brooklyn", "Manhattan", "Brooklyn", "Queens", "Bronx", "Manhattan", "Brooklyn", "Brooklyn", "Queens", "Queens", "Brooklyn", "Brooklyn", "Queens", "Brooklyn", "Brooklyn", "Brooklyn", "Brooklyn", "Bronx", "Bronx", "Queens", "Brooklyn", "Bronx", "Brooklyn", "Brooklyn", "Bronx", "Brooklyn", "Brooklyn", "Manhattan", "Bronx", "Manhattan", "Queens", "Brooklyn", "Queens", "Brooklyn", "Queens", "Brooklyn", "Manhattan", "Bronx", "Brooklyn", "Bronx", "Bronx", "Brooklyn", "Bronx", "Bronx", "Queens", "Brooklyn", "Brooklyn", "Brooklyn", "Bronx", "Queens", "Brooklyn", "Queens", "Brooklyn", "Brooklyn", "Queens", "Manhattan", "Bronx", "Manhattan", "Manhattan", "Brooklyn", "Bronx", "Bronx", "Bronx", "Brooklyn", "Bronx", "Queens", "Brooklyn", "Brooklyn", "Manhattan", "Brooklyn", "Bronx", "Brooklyn", "Queens", "Queens", "Queens", "Brooklyn", "Brooklyn", "Brooklyn", "Bronx", "Bronx", "Brooklyn", "Bronx", "Brooklyn", "Bronx", "Queens", "Brooklyn", "Brooklyn", "Brooklyn", "Brooklyn", "Brooklyn", "Manhattan", "Bronx", "Brooklyn", "Brooklyn", "Bronx", "Queens", "Queens", "Brooklyn", "Brooklyn", "Bronx", "Brooklyn", "Brooklyn", "Manhattan", "Bronx", "Manhattan", "Bronx", "Brooklyn", "Bronx", "Brooklyn", "Brooklyn", "Brooklyn", "Brooklyn", "Bronx", "Queens", "Queens", "Brooklyn", "Brooklyn", "Bronx", "Queens", "Queens", "Brooklyn", "Bronx", "Queens", "Brooklyn", "Brooklyn", "Bronx", "Queens", "Queens", "Brooklyn", "Brooklyn", "Queens", "Staten Island", "Queens", "Queens", "Queens", "Queens", "Queens", "Queens", "Queens", "Queens"], "subwayStationMaxRidershipWeeklyCount": [846756, 632505, 451839, 393325, 336818, 334387, 330490, 271459, 268392, 267253, 243786, 241382, 234706, 221243, 214546, 208245, 207093, 201721, 199307, 186551, 184051, 174965, 171875, 159929, 153679, 153009, 138388, 137279, 130661, 130554, 126646, 125495, 122992, 122141, 122103, 121597, 120057, 117284, 115071, 114184, 113539, 113021, 112509, 109391, 104969, 104713, 102184, 101596, 99718, 99444, 97798, 97389, 96883, 96525, 93497, 93462, 92586, 92275, 91912, 90267, 87094, 86027, 83690, 83616, 83016, 82650, 81234, 81050, 80693, 79170, 78089, 77858, 77112, 77101, 76504, 76232, 76182, 75964, 75701, 75557, 73869, 72257, 70978, 70899, 70695, 69178, 69029, 68749, 68648, 68218, 67959, 67462, 66860, 65921, 65340, 65016, 64316, 63919, 62986, 61700, 61687, 61622, 61226, 60280, 60252, 60041, 59937, 58072, 57864, 57137, 56861, 56230, 55563, 55207, 54930, 54914, 54778, 54425, 54075, 53906, 53710, 53442, 53371, 52536, 52311, 52022, 51428, 51401, 51278, 49961, 49925, 49915, 49659, 49605, 49393, 49072, 48788, 48326, 47156, 46889, 46524, 46174, 46164, 44869, 44839, 44296, 43933, 43659, 42981, 42813, 42286, 42211, 41736, 41590, 40073, 39885, 39614, 39305, 39298, 38451, 38434, 38338, 38094, 37737, 37389, 37332, 37203, 36570, 36515, 35940, 35278, 35272, 35177, 34936, 34850, 34735, 34466, 34237, 34138, 33823, 33605, 33412, 33257, 33223, 33074, 32725, 32675, 32550, 32500, 32460, 32379, 32051, 31981, 31939, 31795, 31695, 31651, 31191, 30704, 30492, 30262, 30110, 29800, 29762, 29749, 29745, 29725, 29694, 29512, 29475, 29443, 29272, 29246, 29195, 29179, 28463, 28453, 28433, 28077, 27851, 27845, 27697, 27661, 27587, 27372, 27357, 27101, 26713, 26375, 26255, 25899, 25792, 25691, 25554, 25353, 25029, 24938, 24760, 24387, 24381, 24279, 24197, 24182, 24106, 24085, 24073, 24030, 23957, 23915, 23867, 23864, 23646, 23479, 23432, 23427, 23335, 23300, 23237, 23228, 23190, 22802, 22712, 22466, 22398, 22312, 22153, 22133, 22131, 21982, 21914, 21844, 21713, 21366, 21300, 21246, 21200, 21164, 21116, 21115, 20944, 20741, 20631, 20569, 20284, 20211, 20034, 19883, 19722, 19648, 19624, 19567, 19442, 19328, 19273, 19254, 19237, 19236, 19183, 19175, 18957, 18941, 18833, 18598, 18464, 18300, 18214, 18192, 18019, 17975, 17973, 17681, 17237, 17233, 16938, 16936, 16896, 16693, 16668, 16596, 16497, 16480, 16452, 16426, 16398, 16369, 16314, 16206, 15981, 15779, 15564, 15545, 15414, 15200, 15113, 15100, 15082, 14894, 14839, 14786, 14776, 14767, 14723, 14398, 14344, 14339, 14303, 14127, 14104, 14066, 14027, 13973, 13919, 13525, 13493, 13460, 12898, 12858, 12329, 12021, 11771, 11764, 11737, 11712, 11686, 11663, 11648, 11538, 11530, 11365, 11272, 11140, 10651, 10639, 10573, 10562, 10545, 10515, 10472, 10370, 10353, 10084, 10043, 10032, 9984, 9851, 9840, 9640, 9568, 9499, 9468, 9164, 9083, 8896, 8782, 8766, 8719, 8658, 8504, 8370, 8314, 8102, 7958, 7956, 7889, 7735, 7644, 7302, 7212, 7025, 6823, 6360, 6147, 6071, 5679, 4522, 3186, 3007, 2903, 2872, 2867, 2709, 2651, 2237, 1344, 1109, 815], "busWeeklyRidership": 7594573, "busYearlyRidership": 408225280, "busMaxAnnualDateRidership": 1555422, "busMaxAnnualDate": "Wednesday, October 9th, 2024", "busMinAnnualDateRidership": 417229, "busMinAnnualDate": "Wednesday, December 25th, 2024", "busMaxDailyRidershipWeekly": 1275936, "busMaxDailyDateWeekly": "Tuesday, January 7th, 2025", "busMaxAnnualDay": "Tuesday", "busMaxMeanDayRidership": 1309078.6538461538, "busMinAnnualDay": "Sunday", "busMinMeanDayRidership": 649649.1923076923, "busRouteMaxRidershipWeeklyRoute": ["Q58", "M15-SBS", "B6", "Q65", "Q27", "Q25", "M15", "M101", "Q23", "Q10", "B41", "M86-SBS", "Q46", "Q66", "B35", "Q44-SBS", "B1", "M4", "B38", "Q17", "B8", "M96", "Q60", "M14D-SBS", "B82", "Bx12-SBS", "M3", "Bx9", "B9", "M7", "M11", "Bx19", "M102", "Bx36", "Q43", "M31", "M1", "B63", "B68", "B46", "M103", "B3", "M42", "S79-SBS", "Bx7", "B44", "Q69", "M79-SBS", "Q54", "M23-SBS", "Q111", "B15", "Q12", "Q88", "B36", "Q32", "Q49", "Q53-SBS", "B11", "Q28", "Q5", "B46-SBS", "M2", "B103", "Q47", "B82-SBS", "Q18", "B52", "M60-SBS", "Q20A", "B49", "Q85", "B44-SBS", "B61", "Q64", "Q38", "Bx2", "B12", "M104", "Q59", "M66", "M57", "Q33", "B26", "Q30", "M14A-SBS", "Q13", "Bx1", "Q83", "M100", "Q4", "Bx3", "B43", "M116", "Bx10", "Q55", "B54", "M125", "B70", "S53", "Q3", "M5", "B62", "Q37", "Bx11", "Q72", "M34A-SBS", "Bx35", "B17", "Bx22", "B57", "Bx39", "B4", "M34-SBS", "B47", "B60", "B16", "Bx13", "B25", "Q36", "Q56", "Bx21", "B13", "Q114", "Q20B", "Q29", "M9", "Q34", "M10", "Q41", "Q24", "Q31", "Q39", "Q110", "SIM1C", "B100", "Q2", "Bx15", "B64", "Bx28", "Bx42", "Bx40", "Bx12", "Q76", "B67", "Bx6", "Bx5", "Bx6-SBS", "Q77", "B69", "M72", "B20", "Q16", "Q19", "Q112", "Bx41-SBS", "Bx16", "B83", "S78", "Q100", "Bx31", "Q84", "B7", "S44", "Q40", "Q52-SBS", "Q1", "Q50", "Q101", "Q22", "Q11", "S46", "Bx41", "Q15A", "Bx17", "B45", "Bx8", "S48", "Bx38", "B14", "BxM7", "S74", "Q48", "Q113", "Bx27", "B65", "Q15", "Bx4", "Bx30", "B48", "Bx23", "S93", "Q21", "B74", "S40", "B31", "Q102", "Q35", "Q67", "Q104", "Bx4A", "S61", "Bx32", "B24", "S62", "BxM9", "X28", "X27", "M55", "B37", "SIM4C", "B2", "Bx34", "SIM1", "S59", "S76", "BxM8", "Bx26", "SIM10", "M22", "M106", "S51", "M50", "BxM10", "QM15", "Bx25", "M20", "SIM8", "S52", "SIM33C", "SIM6", "BxM1", "Q103", "M21", "M12", "M98", "QM5", "SIM3C", "B42", "M8", "Q26", "BxM11", "BM1", "B32", "QM2", "SIM4", "SIM34", "SIM26", "Bx18B", "Bx33", "SIM15", "X37", "SIM2", "Q42", "BM2", "SIM25", "BxM3", "X38", "S57", "SIM11", "QM20", "Bx18A", "BxM6", "SIM22", "BM3", "BM5", "S66", "Bx29", "BxM2", "SIM30", "SIM5", "SIM3", "SIM7", "QM6", "S98", "SIM31", "S90", "BxM4", "BM4", "QM34", "QM24", "Bx24", "SIM33", "SIM35", "QM4", "S91", "QM16", "QM25", "QM7", "S96", "Bx20", "X63", "QM17", "SIM32", "S54", "S94", "QM8", "QM11", "SIM23", "S92", "SIM9", "SIM24", "S42", "QM35", "X68", "QM32", "B84", "S89", "BxM18", "Bx46", "QM12", "S56", "SIM8X", "QM1", "X64", "QM10", "QM42", "QM21", "QM18", "QM40", "B39", "SIM4X", "Q70-SBS", "QM44", "QM31", "S55", "S81", "QM36", "M35", "S84", "S86", "QM3", "J90", "Bx90", "B90", "B93", "B94", "B96", "B98", "B99", "B101", "BX92", "D90", "L90", "L91", "L92", "M90", "Q90", "Q92", "Q93", "Q96", "Q107", "Q108"], "busRouteMaxRidershipWeeklyBorough": ["Queens", "Manhattan", "Brooklyn", "Queens", "Queens", "Queens", "Manhattan", "Manhattan", "Queens", "Queens", "Brooklyn", "Manhattan", "Queens", "Queens", "Brooklyn", "Queens", "Brooklyn", "Manhattan", "Brooklyn", "Queens", "Brooklyn", "Manhattan", "Queens", "Manhattan", "Brooklyn", "Bronx", "Manhattan", "Bronx", "Brooklyn", "Manhattan", "Manhattan", "Bronx", "Manhattan", "Bronx", "Queens", "Manhattan", "Manhattan", "Brooklyn", "Brooklyn", "Brooklyn", "Manhattan", "Brooklyn", "Manhattan", "Staten Island", "Bronx", "Brooklyn", "Queens", "Manhattan", "Queens", "Manhattan", "Queens", "Brooklyn", "Queens", "Queens", "Brooklyn", "Queens", "Queens", "Queens", "Brooklyn", "Queens", "Queens", "Brooklyn", "Manhattan", "Brooklyn", "Queens", "Brooklyn", "Queens", "Brooklyn", "Manhattan", "Queens", "Brooklyn", "Queens", "Brooklyn", "Brooklyn", "Queens", "Queens", "Bronx", "Brooklyn", "Manhattan", "Queens", "Manhattan", "Manhattan", "Queens", "Brooklyn", "Queens", "Manhattan", "Queens", "Bronx", "Queens", "Manhattan", "Queens", "Bronx", "Brooklyn", "Manhattan", "Bronx", "Queens", "Brooklyn", "Manhattan", "Brooklyn", "Staten Island", "Queens", "Manhattan", "Brooklyn", "Queens", "Bronx", "Queens", "Manhattan", "Bronx", "Brooklyn", "Bronx", "Brooklyn", "Bronx", "Brooklyn", "Manhattan", "Brooklyn", "Brooklyn", "Brooklyn", "Bronx", "Brooklyn", "Queens", "Queens", "Bronx", "Brooklyn", "Queens", "Queens", "Queens", "Manhattan", "Queens", "Manhattan", "Queens", "Queens", "Queens", "Queens", "Queens", "Staten Island - Manhattan Express", "Brooklyn", "Queens", "Bronx", "Brooklyn", "Bronx", "Bronx", "Bronx", "Bronx", "Queens", "Brooklyn", "Bronx", "Bronx", "Bronx", "Queens", "Brooklyn", "Manhattan", "Brooklyn", "Queens", "Queens", "Queens", "Bronx", "Bronx", "Brooklyn", "Staten Island", "Queens", "Bronx", "Queens", "Brooklyn", "Staten Island", "Queens", "Queens", "Queens", "Queens", "Queens", "Queens", "Queens", "Staten Island", "Bronx", "Queens", "Bronx", "Brooklyn", "Bronx", "Staten Island", "Bronx", "Brooklyn", "Bronx - Manhattan Express", "Staten Island", "Queens", "Queens", "Bronx", "Brooklyn", "Queens", "Bronx", "Bronx", "Brooklyn", "Bronx", "Staten Island", "Queens", "Brooklyn", "Staten Island", "Brooklyn", "Queens", "Queens", "Queens", "Queens", "Bronx", "Staten Island", "Bronx", "Brooklyn", "Staten Island", "Bronx - Manhattan Express", "Brooklyn/Queens - Midtown Manhattan Express", "Brooklyn/Queens - Midtown Manhattan Express", "Manhattan", "Brooklyn", "Staten Island - Manhattan Express", "Brooklyn", "Bronx", "Staten Island - Manhattan Express", "Staten Island", "Staten Island", "Bronx - Manhattan Express", "Bronx", "Staten Island - Manhattan Express", "Manhattan", "Manhattan", "Staten Island", "Manhattan", "Bronx - Manhattan Express", "Queens - Manhattan Express", "Bronx", "Manhattan", "Staten Island - Manhattan Express", "Staten Island", "Staten Island - Manhattan Express", "Staten Island - Manhattan Express", "Bronx - Manhattan Express", "Queens", "Manhattan", "Manhattan", "Manhattan", "Queens - Manhattan Express", "Staten Island - Manhattan Express", "Brooklyn", "Manhattan", "Queens", "Bronx - Manhattan Express", "Brooklyn - Manhattan Express", "Brooklyn", "Queens - Manhattan Express", "Staten Island - Manhattan Express", "Staten Island - Manhattan Express", "Staten Island - Manhattan Express", "Bronx", "Bronx", "Staten Island - Manhattan Express", "Brooklyn/Queens - Midtown Manhattan Express", "Staten Island - Manhattan Express", "Queens", "Brooklyn - Manhattan Express", "Staten Island - Manhattan Express", "Bronx - Manhattan Express", "Brooklyn/Queens - Midtown Manhattan Express", "Staten Island", "Staten Island - Manhattan Express", "Queens - Manhattan Express", "Bronx", "Bronx - Manhattan Express", "Staten Island - Manhattan Express", "Brooklyn - Manhattan Express", "Brooklyn - Manhattan Express", "Staten Island", "Bronx", "Bronx - Manhattan Express", "Staten Island - Manhattan Express", "Staten Island - Manhattan Express", "Staten Island - Manhattan Express", "Staten Island - Manhattan Express", "Queens - Manhattan Express", "Staten Island", "Staten Island - Manhattan Express", "Staten Island", "Bronx - Manhattan Express", "Brooklyn - Manhattan Express", "Queens - Manhattan Express", "Queens - Manhattan Express", "Bronx", "Staten Island - Manhattan Express", "Staten Island - Manhattan Express", "Queens - Manhattan Express", "Staten Island", "Queens - Manhattan Express", "Queens - Manhattan Express", "Queens - Manhattan Express", "Staten Island", "Bronx", "Brooklyn/Queens - Midtown Manhattan Express", "Queens - Manhattan Express", "Staten Island - Manhattan Express", "Staten Island", "Staten Island", "Queens - Manhattan Express", "Queens - Manhattan Express", "Staten Island - Manhattan Express", "Staten Island", "Staten Island - Manhattan Express", "Staten Island - Manhattan Express", "Staten Island", "Queens - Manhattan Express", "Brooklyn/Queens - Midtown Manhattan Express", "Queens - Manhattan Express", "Brooklyn", "Staten Island", "Bronx - Manhattan Express", "Bronx", "Queens - Manhattan Express", "Staten Island", "Staten Island - Manhattan Express", "Queens - Manhattan Express", "Brooklyn/Queens - Midtown Manhattan Express", "Queens - Manhattan Express", "Queens - Manhattan Express", "Queens - Manhattan Express", "Queens - Manhattan Express", "Queens - Manhattan Express", "Brooklyn", "Staten Island - Manhattan Express", "Queens", "Queens - Manhattan Express", "Queens - Manhattan Express", "Staten Island", "Staten Island", "Queens - Manhattan Express", "Manhattan", "Staten Island", "Staten Island", "Queens - Manhattan Express", "J Train Shuttle Bus", "Bronx", "Brooklyn", "Brooklyn", "Brooklyn", "Brooklyn", "Brooklyn", "Brooklyn", "Brooklyn", "Bronx", "D Train Shuttle Bus", "L Train Shuttle Bus", "L Train Shuttle Bus", "L Train Shuttle Bus", "Manhattan", "Queens", "Queens", "Queens", "Queens", "Queens", "Queens"], "busRouteMaxRidershipWeeklyCount": [128958, 121446, 101362, 96787, 92922, 88595, 87474, 79055, 78307, 76853, 75330, 75148, 73652, 72395, 71526, 68596, 68331, 64960, 63903, 62988, 61844, 58778, 58108, 57813, 57429, 55896, 54653, 54504, 53344, 51631, 51583, 50124, 49769, 49662, 49353, 49296, 49102, 48454, 47355, 47009, 45964, 45458, 45391, 45364, 44970, 44692, 44348, 44321, 43782, 43714, 43476, 43146, 43026, 43026, 41444, 41219, 41040, 40820, 40663, 39967, 39783, 38838, 38656, 38449, 38444, 37801, 37576, 37041, 36607, 36504, 35953, 35526, 35024, 34735, 34651, 34303, 34153, 32397, 32396, 32345, 32108, 31939, 31850, 31795, 31759, 31493, 31372, 30787, 30651, 30633, 30589, 30408, 30332, 30240, 30143, 29949, 29308, 29268, 29219, 28767, 28766, 28612, 28546, 28541, 28340, 28211, 27638, 27106, 27094, 26986, 26615, 26536, 26321, 25653, 25546, 25389, 24879, 24333, 24130, 23943, 23178, 23123, 22858, 22778, 22765, 22415, 22360, 22268, 22225, 22217, 21743, 21723, 21341, 21181, 21130, 20839, 20784, 20760, 20649, 20584, 20391, 20363, 20267, 19735, 19468, 19341, 19246, 19195, 18678, 18225, 17872, 17676, 17155, 17155, 17059, 16953, 16859, 16448, 16198, 16028, 15564, 15551, 15471, 15348, 15256, 14887, 14761, 14745, 14627, 14537, 14413, 14353, 14305, 14143, 13928, 13759, 13724, 13600, 13510, 13472, 13391, 13114, 12982, 12926, 12915, 12888, 12662, 12548, 12276, 12027, 11666, 11617, 11563, 11497, 11207, 11129, 11096, 10701, 10596, 10553, 10396, 10129, 10058, 10000, 9849, 9805, 9483, 9377, 9351, 9302, 9127, 8959, 8936, 8933, 8843, 8717, 8705, 8693, 8667, 8642, 8631, 8589, 8212, 8168, 8025, 7963, 7949, 7772, 7398, 7305, 6730, 6723, 6384, 6205, 6198, 5860, 5841, 5516, 5475, 5471, 5331, 5275, 5000, 4885, 4846, 4809, 4568, 4440, 4403, 4391, 4382, 4300, 4272, 4167, 4060, 3971, 3917, 3914, 3878, 3868, 3805, 3803, 3730, 3714, 3575, 3544, 3541, 3531, 3513, 3470, 3448, 3437, 3178, 2981, 2771, 2765, 2569, 2450, 2438, 2437, 2428, 2139, 2134, 2130, 2128, 2127, 2085, 2069, 2053, 2041, 2016, 1999, 1971, 1937, 1913, 1884, 1830, 1824, 1794, 1782, 1777, 1583, 1505, 1500, 1431, 1381, 1336, 1302, 1147, 1120, 1102, 1024, 962, 915, 912, 892, 781, 724, 678, 660, 659, 649, 629, 629, 614, 574, 554, 551, 500, 462, 427, 415, 3, 1, 0, 0, 0, 0, 0, 0, 0, 0, 0, 0, 0, 0, 0, 0, 0, 0, 0, 0, 0], "tramWeeklyRidership": 47447, "tramMaxDailyRidershipWeekly": 9464.0, "tramMaxDailyDateWeekly": "Friday, January 3rd, 2025"}